ingestion/__init__.py
ingestion/parametros.py
ingestion/start.py
ingestion/banco_dados/__init__.py
ingestion/banco_dados/conexao_banco.py
ingestion/banco_dados/ssl_ca_file/__init__.py
ingestion/banco_dados/ssl_ca_file/iotbd.crt.pem
ingestion/utils/__init__.py
ingestion/utils/io_container_data.py
ingestion-0.0.42.dist-info/METADATA
ingestion-0.0.42.dist-info/WHEEL
ingestion-0.0.42.dist-info/top_level.txt
ingestion-0.0.42.dist-info/RECORD
