Metadata-Version: 2.1
Name: ingestion
Version: 0.0.42
Summary: Ingestão de dados
Author: Jefferson Farias
Author-email: jefferson@fb.com
Keywords: ingestion
Classifier: Development Status :: 2 - Pre-Alpha
Classifier: Intended Audience :: Developers
Classifier: Natural Language :: English
Classifier: Programming Language :: Python :: 3.9
Requires-Python: >=3.9
Requires-Dist: azure-keyvault-secrets (==4.4.0)
Requires-Dist: azure-storage-blob (==12.12.0)
Requires-Dist: pandas (==1.4.2)
Requires-Dist: openpyxl (==3.0.9)
Requires-Dist: xlrd (==2.0.1)
Requires-Dist: sqlalchemy (==1.4.37)
Requires-Dist: mysql-connector-python (==8.0.13)
Requires-Dist: adlfs (==2022.4.0)
Requires-Dist: pyarrow (==8.0.0)
